accera/acc-vulkan-runtime-wrappers.dll
accera/acc-vulkan-runtime-wrappers.lib
accera/bin/acc-translate.exe
accera/gpu/__init__.py
accera_gpu-1.2.29.dist-info/LICENSE
accera_gpu-1.2.29.dist-info/METADATA
accera_gpu-1.2.29.dist-info/WHEEL
accera_gpu-1.2.29.dist-info/top_level.txt
accera_gpu-1.2.29.dist-info/RECORD
